gym_voltorb_flip/__init__.py
gym_voltorb_flip/envs/__init__.py
gym_voltorb_flip/envs/voltorb_flip_env.py
gym_voltorb_flip-0.2.4.dev0.dist-info/WHEEL
gym_voltorb_flip-0.2.4.dev0.dist-info/METADATA
gym_voltorb_flip-0.2.4.dev0.dist-info/RECORD
