Metadata-Version: 2.1
Name: gym-voltorb-flip
Version: 0.2.4.dev0
Summary: A VoltorbFlip environment
License: MIT
Author: Antonio Feregrino
Author-email: antonio.feregrino@gmail.com
Requires-Python: >=3.6,<4.0
Classifier: License :: OSI Approved :: MIT License
Classifier: Programming Language :: Python :: 3
Classifier: Programming Language :: Python :: 3.6
Classifier: Programming Language :: Python :: 3.7
Classifier: Programming Language :: Python :: 3.8
Requires-Dist: gym (>=0.16.0,<0.17.0)
Requires-Dist: voltorb-flip (>=0.2.0.dev0,<0.3.0)
